neuralstockprophet/__init__.py
neuralstockprophet/arima.py
neuralstockprophet/dataset.py
neuralstockprophet/decompose.py
neuralstockprophet/model.py
neuralstockprophet/portfolio.py
neuralstockprophet/prophet.py
neuralstockprophet/risk_strategy.py
neuralstockprophet/utils.py
neuralstockprophet-0.0.3.dist-info/METADATA
neuralstockprophet-0.0.3.dist-info/WHEEL
neuralstockprophet-0.0.3.dist-info/licenses/LICENSE
neuralstockprophet-0.0.3.dist-info/RECORD
