Metadata-Version: 2.3
Name: neuralstockprophet
Version: 0.0.3
Summary: LSTM-ARIMA with attention mechanisms and multiplicative decomposition for sophisticated stock forecasting.
Project-URL: Repository, https://github.com/lucaswychan/neural-stock-prophet
Author-email: Lucas Chan <chanconan@gmail.com>
Maintainer-email: Lucas Chan <chanconan@gmail.com>
License: MIT License
License-File: LICENSE
Keywords: ARIMA,LSTM,attention,forecasting,multiplicative decomposition,stock
Classifier: Development Status :: 3 - Alpha
Classifier: Intended Audience :: Developers
Classifier: License :: OSI Approved :: MIT License
Classifier: Natural Language :: English
Classifier: Operating System :: OS Independent
Classifier: Programming Language :: Python :: 3 :: Only
Classifier: Programming Language :: Python :: 3.8
Classifier: Programming Language :: Python :: 3.9
Classifier: Programming Language :: Python :: 3.10
Classifier: Programming Language :: Python :: 3.11
Classifier: Programming Language :: Python :: 3.12
Classifier: Topic :: Scientific/Engineering :: Artificial Intelligence
Requires-Python: >=3.8
Requires-Dist: empyrical
Requires-Dist: jax
Requires-Dist: jaxlib
Requires-Dist: numpy
Requires-Dist: pandas
Requires-Dist: quadprog
Requires-Dist: riskparityportfolio
Requires-Dist: scikit-learn
Requires-Dist: scipy
Requires-Dist: statsmodels
Requires-Dist: ta
Requires-Dist: tensorflow
Requires-Dist: tensorflow-metal
Requires-Dist: tqdm
Requires-Dist: yfinance
Provides-Extra: lint
Requires-Dist: black; extra == 'lint'
Requires-Dist: flake8; extra == 'lint'
Provides-Extra: tests
Requires-Dist: pytest; extra == 'tests'
Requires-Dist: pytest-cov; extra == 'tests'
